autograd_minimize/__init__.py
autograd_minimize/base_wrapper.py
autograd_minimize/jax_wrapper.py
autograd_minimize/scipy_minimize.py
autograd_minimize/tf_wrapper.py
autograd_minimize/torch_wrapper.py
autograd_minimize-0.3.0.dist-info/LICENSE
autograd_minimize-0.3.0.dist-info/METADATA
autograd_minimize-0.3.0.dist-info/WHEEL
autograd_minimize-0.3.0.dist-info/top_level.txt
autograd_minimize-0.3.0.dist-info/RECORD
