Metadata-Version: 2.1
Name: autograd-minimize
Version: 0.3.0
Summary: A wrapper of scipy minimize with automatic gradient and hessian computation.
Home-page: https://github.com/brunorigal/autograd_minimize
Author: Bruno Rigal
Classifier: Programming Language :: Python :: 3
Classifier: License :: OSI Approved :: MIT License
Classifier: Operating System :: OS Independent
License-File: LICENSE
Requires-Dist: scipy
